Metadata-Version: 1.0
Name: facebook-events-scraper
Version: 0.0.1
Summary: A simple tool to scrape Facebook events using Selenium
Home-page: UNKNOWN
Author: ZhouZ-1
Author-email: UNKNOWN
License: MIT
Platform: UNKNOWN
